PyMata/__init__.py
PyMata/pymata.py
PyMata/pymata_command_handler.py
PyMata/pymata_serial.py
PyMata-2.20.dist-info/LICENSE.txt
PyMata-2.20.dist-info/METADATA
PyMata-2.20.dist-info/WHEEL
PyMata-2.20.dist-info/top_level.txt
PyMata-2.20.dist-info/RECORD
