Metadata-Version: 2.1
Name: PyMata
Version: 2.20
Summary: A Python Protocol Abstraction Library For Arduino Firmata
Home-page: https://github.com/MrYsLab/PyMata
Author: Alan Yorinks
Author-email: MisterYsLab@gmail.com
License: UNKNOWN
Download-URL: https://github.com/MrYsLab/PyMata
Keywords: Firmata,Arduino,Protocol
Platform: UNKNOWN
Classifier: Development Status :: 5 - Production/Stable
Classifier: Environment :: Other Environment
Classifier: Intended Audience :: Developers
Classifier: Intended Audience :: Education
Classifier: License :: OSI Approved :: GNU Affero General Public License v3 or later (AGPLv3+)
Classifier: Operating System :: OS Independent
Classifier: Programming Language :: Python
Classifier: Programming Language :: Python :: 2.7
Classifier: Programming Language :: Python :: 3.5
Classifier: Topic :: Utilities
Classifier: Topic :: Home Automation
Requires-Dist: pyserial
